CHANGES.txt
MANIFEST.in
README.rst
doc.requirements.txt
faq.txt
install.txt
license.txt
news.txt
requirements.txt
setup.cfg
setup.py
thanks.txt
todo.txt
./versio/__init__.py
./versio/comparable_mixin.py
./versio/version.py
./versio/version_scheme.py
Versio.egg-info/PKG-INFO
Versio.egg-info/SOURCES.txt
Versio.egg-info/dependency_links.txt
Versio.egg-info/requires.txt
Versio.egg-info/top_level.txt
tests/version_test.py
tests/versionstr_test.py