Metadata-Version: 1.1
Name: Versio
Version: 0.4.0
Summary: Version manipulation library.
Home-page: https://github.com/royw/Versio
Author: Roy Wright
Author-email: roy@wright.org
License: license.txt
Download-URL: https://github.com/royw/Versio/archive/versio-0.4.0.tar.gz
Keywords: version,PEP 440
Platform: UNKNOWN
Classifier: Development Status :: 5 - Production/Stable
Classifier: Intended Audience :: Developers
Classifier: License :: OSI Approved :: MIT License
Classifier: Natural Language :: English
Classifier: Operating System :: OS Independent
Classifier: Programming Language :: Python
Classifier: Topic :: Software Development
